camel_toolkits_mcp/__init__.py
camel_toolkits_mcp/router.py
camel_toolkits_mcp/server.py
camel_toolkits_mcp-0.1.2.dist-info/METADATA
camel_toolkits_mcp-0.1.2.dist-info/WHEEL
camel_toolkits_mcp-0.1.2.dist-info/entry_points.txt
camel_toolkits_mcp-0.1.2.dist-info/top_level.txt
camel_toolkits_mcp-0.1.2.dist-info/RECORD
