Metadata-Version: 2.4
Name: camel-toolkits-mcp
Version: 0.1.2
Summary: A server that exports Camel toolkits as MCP-compatible tools
Author-email: Xiaotian Jin <jin.xiaotian.kim@gmail.com>
License: MIT
Project-URL: Homepage, https://github.com/MuggleJinx/Camel-toolkits-mcp
Project-URL: Bug Tracker, https://github.com/MuggleJinx/Camel-toolkits-mcp/issues
Classifier: Development Status :: 4 - Beta
Classifier: Intended Audience :: Developers
Classifier: License :: OSI Approved :: MIT License
Classifier: Programming Language :: Python :: 3
Classifier: Programming Language :: Python :: 3.10
Classifier: Programming Language :: Python :: 3.11
Classifier: Programming Language :: Python :: 3.12
Classifier: Topic :: Software Development :: Libraries :: Python Modules
Requires-Python: >=3.10
Requires-Dist: camel-ai>=0.2.58
Requires-Dist: mcp[cli]>=1.8.1
Requires-Dist: numpy>=2.2.5
Requires-Dist: pandas>=2.2.3
Requires-Dist: pillow>=11.2.1
Requires-Dist: pyowm>=3.3.0
Requires-Dist: pyyaml>=6.0.2
Requires-Dist: requests-oauthlib>=2.0.0
Requires-Dist: sqlalchemy>=2.0.40
Provides-Extra: dev
Requires-Dist: pytest>=7.0.0; extra == "dev"
Requires-Dist: pytest-cov>=4.0.0; extra == "dev"
Requires-Dist: black>=23.0.0; extra == "dev"
Requires-Dist: isort>=5.12.0; extra == "dev"
Requires-Dist: flake8>=6.0.0; extra == "dev"
Requires-Dist: build>=0.10.0; extra == "dev"
Requires-Dist: twine>=4.0.2; extra == "dev"
